datapipes/__init__.py
datapipes-0.0.2.dist-info/LICENSE
datapipes-0.0.2.dist-info/WHEEL
datapipes-0.0.2.dist-info/METADATA
datapipes-0.0.2.dist-info/RECORD
